earnings/__init__.py
earnings/constants.py
earnings/main.py
earnings/utils.py
earnings-1.1.0.dist-info/AUTHORS
earnings-1.1.0.dist-info/LICENSE
earnings-1.1.0.dist-info/METADATA
earnings-1.1.0.dist-info/WHEEL
earnings-1.1.0.dist-info/top_level.txt
earnings-1.1.0.dist-info/RECORD
