Metadata-Version: 2.1
Name: earnings
Version: 1.1.0
Summary: Equity earnings Python package (confirmed calendar, news articles, earnings transcripts, ...)
Home-page: https://github.com/lcsrodriguez/earnings
Author: Lucas RODRIGUEZ
Author-email: lcsrodriguez@pm.me
License: MIT
Classifier: Programming Language :: Python :: 3
Classifier: License :: OSI Approved :: MIT License
Classifier: Operating System :: OS Independent
Requires-Python: >=3.10
License-File: LICENSE
License-File: AUTHORS
Requires-Dist: requests (==2.31.0)
Requires-Dist: pandas (==2.1.3)
